{
  "run_id": "gha_20260716_203208Z",
  "scheduled_at_utc": "2026-07-16T20:32:08Z",
  "started_at_utc": "2026-07-16T20:32:08Z",
  "completed_at_utc": "2026-07-16T20:40:37Z",
  "source": "gha",
  "exit_code": 0,
  "rows_fetched": 26,
  "rows_added": 26,
  "stations_seen": 26,
  "station_ids_seen": [
    "S124",
    "S125",
    "S126",
    "S127",
    "S128",
    "S129",
    "S132",
    "S135",
    "S137",
    "S139",
    "S140",
    "S141",
    "S142",
    "S143",
    "S144",
    "S145",
    "S146",
    "S147",
    "S148",
    "S149",
    "S150",
    "S151",
    "S153",
    "S180",
    "S184",
    "S187"
  ],
  "warnings": [
    "openmeteo station_S132: ReadTimeout(ReadTimeoutError(\"HTTPSConnectionPool(host='api.open-meteo.com', port=443): Read timed out. (read timeout=35)\"))",
    "openmeteo station_S144: ReadTimeout(ReadTimeoutError(\"HTTPSConnectionPool(host='api.open-meteo.com', port=443): Read timed out. (read timeout=35)\"))",
    "openmeteo station_S153: ReadTimeout(ReadTimeoutError(\"HTTPSConnectionPool(host='api.open-meteo.com', port=443): Read timed out. (read timeout=35)\"))"
  ],
  "api_status": "warn",
  "commit_sha": "d932cbe24fa88c5ed52fb866aaa423877e5a09b2",
  "chunk_path": "data/calibration/v11/live_chunks/wbgt_pairs_2026-07-16.csv.gz"
}