{
  "run_id": "gha_20260719_202926Z",
  "scheduled_at_utc": "2026-07-19T20:29:25Z",
  "started_at_utc": "2026-07-19T20:29:26Z",
  "completed_at_utc": "2026-07-19T20:37:19Z",
  "source": "gha",
  "exit_code": 0,
  "rows_fetched": 25,
  "rows_added": 25,
  "stations_seen": 25,
  "station_ids_seen": [
    "S124",
    "S126",
    "S127",
    "S128",
    "S129",
    "S132",
    "S135",
    "S137",
    "S139",
    "S140",
    "S141",
    "S142",
    "S143",
    "S144",
    "S145",
    "S146",
    "S147",
    "S148",
    "S149",
    "S150",
    "S151",
    "S153",
    "S180",
    "S184",
    "S187"
  ],
  "warnings": [
    "openmeteo station_S135: ReadTimeout(ReadTimeoutError(\"HTTPSConnectionPool(host='api.open-meteo.com', port=443): Read timed out. (read timeout=35)\"))",
    "openmeteo station_S145: ReadTimeout(ReadTimeoutError(\"HTTPSConnectionPool(host='api.open-meteo.com', port=443): Read timed out. (read timeout=35)\"))",
    "openmeteo station_S153: ReadTimeout(ReadTimeoutError(\"HTTPSConnectionPool(host='api.open-meteo.com', port=443): Read timed out. (read timeout=35)\"))"
  ],
  "api_status": "warn",
  "commit_sha": "37083348e463ae78fd6ad52a148e1ba0e60456d5",
  "chunk_path": "data/calibration/v11/live_chunks/wbgt_pairs_2026-07-19.csv.gz"
}